<?xml version="1.0" encoding="UTF-8"?>
<root>
<config_name>从旧表web_members_op,web_memberfield_op中导入到新表web_members_search</config_name>
<table>
	<name>web_members_search</name><!-- 要插入数据的表 -->
	<pretable>web_members_op,web_memberfield_op</pretable><!-- 数据来源的表 -->
	<step>1000</step><!-- 一次插入多少条 -->
	<fk>web_members_op.uid=web_memberfield_op.uid</fk><!-- 来源表关联 -->
		<field>
		<isint>1</isint>
		<name>uid</name>
		<from>web_members_op.uid</from>
	</field>
	<field>
		<name>nickname</name>
		<from>web_members_op.nickname</from>
	</field>
	<field>
		<name>telphone</name>
		<from>web_members_op.telphone</from>
	</field>
	<field>
		<name>nickname2</name>
		<from>web_members_op.nickname2</from>
	</field>
	<field>
		<name>password</name>
		<from>web_members_op.password</from>
	</field>
	<field>
		<name>truename</name>
		<from>web_memberfield_op.truename</from>
	</field>
	<field>
		<isint>1</isint>
		<name>gender</name>
		<from>web_members_op.gender</from>
		<rule>
			<type>1</type>
			<value>-1->0</value>
		</rule>
	</field>
	<field>
		<isint>1</isint>
		<name>birthyear</name>
		<from>web_members_op.birthyear</from>
		<rule>
			<type>1</type>
			<value>-1->0</value>
		</rule>
	</field>
	<field>
		<isint>1</isint>
		<name>province</name>
		<from>web_members_op.province</from>
		<rule>
		<type>1</type>
		<value>-1->0,-2->2</value>
		</rule>
	</field>
	<field>
		<isint>1</isint>
		<name>city</name>
		<from>web_members_op.city</from>
		<rule>
		<type>1</type>
		<value>-1->0</value>
		</rule>
	</field>
	<field>
		<isint>1</isint>
		<name>marriage</name>
		<from>web_members_op.marriage</from>
		<rule>
			<type>1</type>
			<value>-1->0</value>
		</rule>
	</field>
	<field>
		<isint>1</isint>
		<name>education</name>
		<from>web_members_op.education</from>
		<rule>
			<type>1</type>
			<value>-1->0</value>
		</rule>
	</field>
	<field>
		<isint>1</isint>
		<name>salary</name>
		<from>web_members_op.salary</from>
		<rule>
			<type>1</type>
			<value>-1->0</value>
		</rule>
	</field>
	<field>
		<isint>1</isint>
		<name>house</name>
		<from>web_members_op.house</from>
		<rule>
			<type>1</type>
			<value>-1->0</value>
		</rule>
	</field>
	<field>
		<isint>1</isint>
		<name>children</name>
		<from>web_members_op.children</from>
		<rule>
			<type>1</type>
			<value>-1->0</value>
		</rule>
	</field>
	<field>
		<isint>1</isint>
		<name>height</name>
		<from>web_members_op.height</from>
		<rule>
			<type>1</type>
			<value>-1->0</value>
		</rule>
	</field>
	<field>
		<isint>1</isint>
		<name>s_cid</name>
		<from>web_members_op.s_cid</from>
		<rule>
			<type>1</type>
			<value>-1->10, 0->20, 1->30, 2->40, 3->50</value>
		</rule>
	</field>
	<field>
		<isint>1</isint>
		<name>images_ischeck</name>
		<from>web_members_op.images_ischeck</from>
		<rule>
			<type>1</type>
			<value>-1->0, 0->2</value>
		</rule>
	</field>
	<field>
		<isint>1</isint>
		<name>is_lock</name>
		<from>web_members_op.is_lock</from>
	</field>
	<field>
		<isint>1</isint>
		<name>pic_num</name>
		<from>web_members_op.pic_num</from>
		<rule>
			<type>1</type>
			<value>-1->0</value>
		</rule>
	</field>
	<field>
		<isint>1</isint>
		<name>city_star</name>
		<from>web_members_op.city_star</from>
		<rule>
			<type>1</type>
			<value>-1->0</value>
		</rule>
	</field>
	<field>
		<isint>1</isint>
		<name>certification</name>
		<from>web_members_op.certification</from>
		<rule>
			<type>1</type>
			<value>-1->0</value>
		</rule>
	</field>
	<field>
		<isint>1</isint>
		<name>weight</name>
		<from>web_memberfield_op.weight</from>
		<rule>
			<type>1</type>
			<value>-1->0</value>
		</rule>
	</field>
	<field>
		<isint>1</isint>
		<name>body</name>
		<from>web_memberfield_op.body</from>
		<rule>
			<type>1</type>
			<value>-1->0,0->20</value>
		</rule>
	</field>
	<field>
		<isint>1</isint>
		<name>animalyear</name>
		<from>web_memberfield_op.animalyear</from>
		<rule>
			<type>1</type>
			<value>-1->0</value>
		</rule>
	</field>
	<field>
		<isint>1</isint>
		<name>constellation</name>
		<from>web_memberfield_op.constellation</from>
		<rule>
			<type>1</type>
			<value>-1->0</value>
		</rule>
	</field>
	<field>
		<isint>1</isint>
		<name>bloodtype</name>
		<from>web_memberfield_op.bloodtype</from>
		<rule>
			<type>1</type>
			<value>-1->0</value>
		</rule>
	</field>
	<field>
		<isint>1</isint>
		<name>hometownprovince</name>
		<from>web_memberfield_op.hometownprovince</from>
		<rule>
		<type>1</type>
		<value>-1->0,-2->2</value>
		</rule>
	</field>
	<field>
		<isint>1</isint>
		<name>hometowncity</name>
		<from>web_memberfield_op.hometowncity</from>
		<rule>
		<type>1</type>
		<value>-1->0</value>
		</rule>
	</field>
	<field>
		<isint>1</isint>
		<name>nation</name>
		<from>web_memberfield_op.nation</from>
		<rule>
			<type>1</type>
			<value>-1->0</value>
		</rule>
	</field>
	<field>
		<isint>1</isint>
		<name>religion</name>
		<from>web_memberfield_op.religion</from>
		<rule>
			<type>1</type>
			<value>-1->0,0->15</value>
		</rule>
	</field>
	<field>
		<isint>1</isint>
		<name>family</name>
		<from>web_memberfield_op.family</from>
		<rule>
			<type>1</type>
			<value>-1->0</value>
		</rule>
	</field>
	<field>
		<name>language</name>
		<from>web_memberfield_op.language</from>
	</field>
	<field>
		<isint>1</isint>
		<name>smoking</name>
		<from>web_memberfield_op.smoking</from>
		<rule>
			<type>1</type>
			<value>-1->0,0->5</value>
		</rule>
	</field>
	<field>
		<isint>1</isint>
		<name>drinking</name>
		<from>web_memberfield_op.drinking</from>
		<rule>
			<type>1</type>
			<value>-1->0,0->5</value>
		</rule>
	</field>
	<field>
		<isint>1</isint>
		<name>occupation</name>
		<from>web_memberfield_op.occupation</from>
		<rule>
			<type>1</type>
			<value>-1->0</value>
		</rule>
	</field>
	<field>
		<isint>1</isint>
		<name>vehicle</name>
		<from>web_memberfield_op.vehicle</from>
		<rule>
			<type>1</type>
			<value>-1->0</value>
		</rule>
	</field>
	<field>
		<isint>1</isint>
		<name>corptype</name>
		<from>web_memberfield_op.corptype</from>
		<rule>
			<type>1</type>
			<value>-1->0</value>
		</rule>
	</field>
	<field>
		<isint>1</isint>
		<name>wantchildren</name>
		<from>web_memberfield_op.wantchildren</from>
		<rule>
			<type>1</type>
			<value>-1->0</value>
		</rule>
	</field>
	<field>
		<isint>1</isint>
		<name>usertype</name>
		<from>web_members_op.usertype</from>
	</field>
	<field>
		<isint>1</isint>
		<name>regdate</name>
		<from>web_members_op.regdate</from>
	</field>
	<field>
		<name>username</name>
		<from>web_members_op.username</from>
	</field>
	<field>
		<isint>1</isint>
		<name>bgtime</name>
		<from>web_members_op.bgtime</from>
	</field>
	<field>
		<isint>1</isint>
		<name>endtime</name>
		<from>web_members_op.endtime</from>
	</field>
	<field>
		<isint>1</isint>
		<name>sid</name>
		<from>web_members_op.sid</from>
		<rule>
			<type>1</type>
			<value>-1->0</value>
		</rule>
	</field>
	<field>
		<isint>1</isint>
		<name>is_well_user</name>
		<from>web_members_op.is_well_user</from>
		<rule>
			<type>1</type>
			<value>-1->0</value>
		</rule>
	</field>
	<field>
		<isint>1</isint>
		<name>is_vote</name>
		<from>web_members_op.is_vote</from>
		<rule>
			<type>1</type>
			<value>-1->0</value>
		</rule>
	</field>
	<field>
		<isint>1</isint>
		<name>showinformation</name>
		<from>web_members_op.showinformation</from>
	</field>
</table>
</root>